ansible_toolbox/__init__.py
ansible_toolbox/base.py
ansible_toolbox/cmd/__init__.py
ansible_toolbox/cmd/eval.py
ansible_toolbox/cmd/role.py
ansible_toolbox/cmd/task.py
ansible_toolbox/templates/eval.yml
ansible_toolbox/templates/role.yml
ansible_toolbox/templates/tasklist.yml
ansible_toolbox-0.3.dist-info/DESCRIPTION.rst
ansible_toolbox-0.3.dist-info/METADATA
ansible_toolbox-0.3.dist-info/RECORD
ansible_toolbox-0.3.dist-info/WHEEL
ansible_toolbox-0.3.dist-info/entry_points.txt
ansible_toolbox-0.3.dist-info/metadata.json
ansible_toolbox-0.3.dist-info/top_level.txt
