Metadata-Version: 2.0
Name: ansible-toolbox
Version: 0.3
Summary: UNKNOWN
Home-page: https://github.com/larsks/ansible-toolbox
Author: Lars Kellogg-Stedman
Author-email: lars@oddbit.com
License: UNKNOWN
Platform: UNKNOWN
Requires-Dist: jinja2
